MANIFEST.in
README.rst
setup.py
aliyun_python_sdk_acm.egg-info/PKG-INFO
aliyun_python_sdk_acm.egg-info/SOURCES.txt
aliyun_python_sdk_acm.egg-info/dependency_links.txt
aliyun_python_sdk_acm.egg-info/requires.txt
aliyun_python_sdk_acm.egg-info/top_level.txt
aliyunsdkacm/__init__.py
aliyunsdkacm/endpoint.py
aliyunsdkacm/request/__init__.py
aliyunsdkacm/request/v20200206/CreateConfigurationRequest.py
aliyunsdkacm/request/v20200206/CreateNamespaceRequest.py
aliyunsdkacm/request/v20200206/DeleteConfigurationRequest.py
aliyunsdkacm/request/v20200206/DeleteNamespaceRequest.py
aliyunsdkacm/request/v20200206/DeployConfigurationRequest.py
aliyunsdkacm/request/v20200206/DescribeConfigurationRequest.py
aliyunsdkacm/request/v20200206/DescribeNamespaceRequest.py
aliyunsdkacm/request/v20200206/DescribeNamespacesRequest.py
aliyunsdkacm/request/v20200206/UpdateNamespaceRequest.py
aliyunsdkacm/request/v20200206/__init__.py